pyglet_gamemaker/__init__.py
pyglet_gamemaker/menu.py
pyglet_gamemaker/scene.py
pyglet_gamemaker/sprite.py
pyglet_gamemaker/types.py
pyglet_gamemaker/window.py
pyglet_gamemaker/gui/__init__.py
pyglet_gamemaker/gui/button.py
pyglet_gamemaker/gui/text.py
pyglet_gamemaker/gui/text_button.py
pyglet_gamemaker/shapes/__init__.py
pyglet_gamemaker/shapes/hitbox.py
pyglet_gamemaker/shapes/rect.py
pyglet_gamemaker-1.0.1.dist-info/METADATA
pyglet_gamemaker-1.0.1.dist-info/WHEEL
pyglet_gamemaker-1.0.1.dist-info/licenses/LICENSE
pyglet_gamemaker-1.0.1.dist-info/RECORD
