Metadata-Version: 2.4
Name: pyglet-gamemaker
Version: 1.0.1
Summary: pyglet wrapper for making games.
Project-URL: Homepage, https://github.com/Badnameee/pyglet-gamemaker
Project-URL: Issues, https://github.com/Badnameee/pyglet-gamemaker/issues
Author-email: Steven Robles <stevenrrobles13@gmail.com>
License-Expression: MIT
License-File: LICENSE
Classifier: Operating System :: OS Independent
Classifier: Programming Language :: Python :: 3.10
Classifier: Programming Language :: Python :: 3.11
Classifier: Programming Language :: Python :: 3.12
Classifier: Programming Language :: Python :: 3.13
Classifier: Programming Language :: Python :: 3.14
Requires-Python: >=3.10
Requires-Dist: pyglet>=2.1.10
